pltshow.py
pltshow-0.1.3.dist-info/METADATA
pltshow-0.1.3.dist-info/RECORD
pltshow-0.1.3.dist-info/WHEEL
pltshow-0.1.3.dist-info/top_level.txt
